epub_utils/__init__.py
epub_utils/__main__.py
epub_utils/cli.py
epub_utils/container.py
epub_utils/doc.py
epub_utils/exceptions.py
epub_utils/printers.py
epub_utils/content/__init__.py
epub_utils/content/base.py
epub_utils/content/xhtml.py
epub_utils/navigation/__init__.py
epub_utils/navigation/base.py
epub_utils/navigation/nav/__init__.py
epub_utils/navigation/nav/dom.py
epub_utils/navigation/ncx/__init__.py
epub_utils/navigation/ncx/dom.py
epub_utils/package/__init__.py
epub_utils/package/manifest.py
epub_utils/package/metadata.py
epub_utils/package/spine.py
epub_utils-0.1.0a1.dist-info/licenses/LICENSE
epub_utils-0.1.0a1.dist-info/METADATA
epub_utils-0.1.0a1.dist-info/WHEEL
epub_utils-0.1.0a1.dist-info/entry_points.txt
epub_utils-0.1.0a1.dist-info/top_level.txt
epub_utils-0.1.0a1.dist-info/RECORD
