Metadata-Version: 2.4
Name: epub-utils
Version: 0.1.0a1
Summary: A Python CLI and utility library for manipulating EPUB files
Home-page: https://github.com/ernestofgonzalez/epub-utils
Author: Ernesto González
License: Apache License, Version 2.0
Project-URL: Source code, https://github.com/ernestofgonzalez/epub-utils
Project-URL: Issues, https://github.com/ernestofgonzalez/epub-utils/issues
Project-URL: CI, https://github.com/ernestofgonzalez/epub-utils/actions
Project-URL: Changelog, https://github.com/ernestofgonzalez/epub-utils/releases
Classifier: Intended Audience :: Developers
Classifier: Topic :: Software Development :: Libraries
Classifier: Topic :: Utilities
Classifier: Programming Language :: Python :: 3.8
Classifier: Programming Language :: Python :: 3.9
Classifier: Programming Language :: Python :: 3.10
Classifier: Programming Language :: Python :: 3.11
Classifier: Programming Language :: Python :: 3.12
Classifier: Programming Language :: Python :: 3.13
Classifier: Operating System :: Microsoft :: Windows
Classifier: Operating System :: POSIX
Classifier: Operating System :: Unix
Classifier: Operating System :: MacOS
Requires-Python: >=3.8
License-File: LICENSE
Requires-Dist: click
Requires-Dist: lxml
Requires-Dist: packaging
Requires-Dist: pygments
Requires-Dist: PyYAML
Provides-Extra: test
Requires-Dist: pytest; extra == "test"
Provides-Extra: docs
Requires-Dist: sphinx; extra == "docs"
Requires-Dist: sphinx-copybutton; extra == "docs"
Requires-Dist: sphinx-issues; extra == "docs"
Requires-Dist: furo; extra == "docs"
Dynamic: author
Dynamic: classifier
Dynamic: description
Dynamic: description-content-type
Dynamic: home-page
Dynamic: license
Dynamic: license-file
Dynamic: project-url
Dynamic: provides-extra
Dynamic: requires-dist
Dynamic: requires-python
Dynamic: summary
